{
	"title" : "Hickory Veterinary Hospital",
	"htmlClass": "pl",
	"bodyClass": "body",
	"img": {
		"landscape-3x1": {
			"src": "http://placeimg.com/2400/800/animals", 
			"alt": "3x1 Image"
		},
		"landscape-2x1": {
			"src": "http://placeimg.com/1600/800/animals", 
			"alt": "2x1 Image"
		},
		"landscape-3x2": {
			"src": "http://placeimg.com/900/600/animals", 
			"alt": "3x2 Image"
		},
		"square": {
			"src": "http://placeimg.com/800/800/animals", 
			"alt": "Square Thumbnail"
		},
		"portrait-2x3": {
			"src": "http://placeimg.com/600/900/animals", 
			"alt": "2x3 Image"
		}
	},
	"contact" : {
		"phone" : "610-828-3054",
		"address1" : "2303 Hickory Road",
		"address2" : "Plymouth Meeting, PA 19462"
	},
	"headline" : {
		"short" : "Lorem ipsum dolor sit (37 characters)",
		"medium" : "Lorem ipsum dolor sit amet, consectetur adipiscing elit. (72 characters)"
	},
	"excerpt" : {
		"short" : "Lorem ipsum dolor sit amet, consectetur adipisicing elit, sed do eiusmod tempor incididunt ut labore et dolore magna aliqua. Ut enim ad minim veniam",
		"medium" : "Lorem ipsum dolor sit amet, consectetur adipisicing elit, sed do eiusmod tempor incididunt ut labore et dolore magna aliqua. Ut enim ad minim veniam, quis nostrud exercitation ullamco laboris nisi ut aliquip ex ea commodo consequat.",
		"long" : "Lorem ipsum dolor sit amet, consectetur adipisicing elit, sed do eiusmod tempor incididunt ut labore et dolore magna aliqua. Ut enim ad minim veniam, quis nostrud exercitation ullamco laboris nisi ut aliquip ex ea commodo consequat. Duis aute irure dolor in reprehenderit in voluptate velit esse cillum dolore eu fugiat nulla pariatur. Excepteur sint occaecat cupidatat non proident, sunt in culpa qui officia deserunt mollit anim id est laborum."
	},
	"description" : "So, setting about it as methodically as men might smoke out a wasps' nest, the Martians spread this strange stifling vapour over the Londonward country. The horns of the crescent slowly moved apart, until at last they formed a line from Hanwell to Coombe and Malden. All night through their destructive tubes advanced.",
	"url" : "#",
	"name" : {
		"first": "Doctor",
		"last": "Name"
	},
	"service" : "Service",
	"subService" : "Sub-Service",
	"jobTitle" : "Degrees",
	"owner" : {
		"name": "Jessica",
		"last": "L."
	},
	"pet" : {
		"name": "Fido",
		"ailment": "Fractured Leg"
	},
	"year" : {
		"long": "2013",
		"short": "13"
	},
	"month" : {
		"long": "February",
		"short": "Feb",
		"digit": "02"
	},
	"dayofweek" : {
		"long": "Monday",
		"short": "Mon"
	},
	"day" : {
		"long": "10",
		"short": "10",
		"name": "Monday",
		"ordinal": "th"
	},
	"hour" : {
		"long": "01",
		"short": "1",
		"military": "13",
		"ampm": "pm"
	},
	"minute" : {
		"long": "20",
		"short": "20"
	},
	"seconds" : "31",
	"author" : {
		"first-name": "Author",
		"last-name": "Name"
	},
	"hero": true,
	"emergency" : false,
	"touts" : [
		{ },
		{ },
		{ }
	],

	"sidebar" : {
		"title": "Sidebar Title"
	},

	"latest-posts" : [
		{ },
		{ },
		{ },
		{ },
		{ }
	]
}